{
  "name": "Light",
  "colors": {
    "--background": "#f5f5f7",
    "--foreground": "#1a1a1a",
    "--card": "#ffffff",
    "--card-hover": "#f0f0f2",
    "--border": "#e2e2e6",
    "--border-hover": "#b4b4ba",
    "--muted": "#6b6b73",
    "--accent": "#3b3b40"
  },
  "fonts": {
    "--font-sans": "Geist, system-ui, -apple-system, sans-serif",
    "--font-mono": "Geist Mono, ui-monospace, monospace",
    "--font-size-base": "14px",
    "--font-size-sm": "12px",
    "--font-size-lg": "18px"
  },
  "radius": {
    "--radius-sm": "4px",
    "--radius-md": "8px",
    "--radius-lg": "12px"
  },
  "spacing": {
    "--card-padding": "16px",
    "--card-gap": "8px"
  },
  "customCss": ""
}
